README.md
setup.cfg
setup.py
multi_rq/__init__.py
multi_rq/multi_rq.py
multi_rq.egg-info/PKG-INFO
multi_rq.egg-info/SOURCES.txt
multi_rq.egg-info/dependency_links.txt
multi_rq.egg-info/not-zip-safe
multi_rq.egg-info/requires.txt
multi_rq.egg-info/top_level.txt